vld-0.0.1.dist-info/DESCRIPTION.rst
vld-0.0.1.dist-info/METADATA
vld-0.0.1.dist-info/WHEEL
vld-0.0.1.dist-info/metadata.json
vld-0.0.1.dist-info/entry_points.txt
vld-0.0.1.dist-info/RECORD
vld-0.0.1.dist-info/top_level.txt
vld/constants.py
vld/serialization.py
vld/vld.py
vld/objects.py
vld/parse.py
vld/ingredient.py
vld/__init__.py
vld/conversions.py
vld/utils.py
vld/commands/__init__.py
vld/commands/show_ingredients.py
vld/commands/report.py
vld/commands/new_ingredient.py
vld/commands/price.py
vld/commands/count.py
vld/output/__init__.py
vld/output/html.py
