Metadata-Version: 2.0
Name: vld
Version: 0.0.1
Summary: A diet logger.
Home-page: https://github.com/pignacio/vld
Author: Ignacio Rossi
Author-email: rossi.ignacio@gmail.com 
License: GPLv3
Keywords: v,l,d, ,v,a,r, ,l,o,g, ,d,i,e,t,a, ,d,i,e,t, ,c,a,l,o,r,i,e,s
Platform: UNKNOWN
Classifier: Development Status :: 2 - Pre-Alpha
Classifier: Intended Audience :: Developers
Classifier: License :: OSI Approved :: GNU General Public License v3 (GPLv3)
Classifier: Natural Language :: English
Classifier: Programming Language :: Python :: 2
Classifier: Programming Language :: Python :: 2.7
Requires-Dist: cached-property
Requires-Dist: pignacio-scripts
Requires-Dist: unidecode
